LICENSE
README.md
setup.py
flitton_fib_py/__init__.py
flitton_fib_py/version.py
flitton_fib_py/cmd/__init__.py
flitton_fib_py/cmd/fib_numb.py
flitton_fib_py/fib_calcs/__init__.py
flitton_fib_py/fib_calcs/fib_number.py
flitton_fib_py/fib_calcs/fib_numbers.py
packt_fibonacci/__init__.py
python_fib.egg-info/PKG-INFO
python_fib.egg-info/SOURCES.txt
python_fib.egg-info/dependency_links.txt
python_fib.egg-info/entry_points.txt
python_fib.egg-info/requires.txt
python_fib.egg-info/top_level.txt
tests/flitton_fib_py/__init__.py
tests/flitton_fib_py/fib_calcs/__init__.py
tests/flitton_fib_py/fib_calcs/test_fib_number.py
tests/flitton_fib_py/fib_calcs/test_fib_numbers.py