Metadata-Version: 2.1
Name: python-fib
Version: 0.0.2
Summary: Calculates a Fibonacci number
Home-page: https://github.com/alphadecoder/python-fib
Author: alphadecoder
Author-email: alphadecoder@163.com
Classifier: Development Status :: 4 - Beta
Classifier: Programming Language :: Python :: 3
Classifier: Operating System :: OS Independent
Requires-Python: >=3
Provides-Extra: server
License-File: LICENSE
